afsutil/__init__.py
afsutil/__main__.py
afsutil/__resources__.py
afsutil/__version__.py
afsutil/build.py
afsutil/cell.py
afsutil/check.py
afsutil/cli.py
afsutil/cmd.py
afsutil/getdeps.py
afsutil/install.py
afsutil/keytab.py
afsutil/misc.py
afsutil/modreload.py
afsutil/package.py
afsutil/rpm.py
afsutil/service.py
afsutil/transarc.py
afsutil/yum.py
afsutil/system/__init__.py
afsutil/system/common.py
afsutil/system/linux.py
afsutil/system/sunos.py
afsutil-0.8.10.data/scripts/afsutil
afsutil-0.8.10.dist-info/DESCRIPTION.rst
afsutil-0.8.10.dist-info/METADATA
afsutil-0.8.10.dist-info/RECORD
afsutil-0.8.10.dist-info/WHEEL
afsutil-0.8.10.dist-info/metadata.json
afsutil-0.8.10.dist-info/top_level.txt
