Metadata-Version: 2.0
Name: afsutil
Version: 0.8.10
Summary: Utilities to setup OpenAFS clients and servers
Home-page: https://github.com/openafs-contrib/afsutil
Author: Michael Meffie
Author-email: mmeffie@sinenomine.net
License: BSD
Platform: UNKNOWN
Classifier: Development Status :: 4 - Beta
Classifier: Environment :: Console
Classifier: Intended Audience :: Developers
Classifier: License :: OSI Approved :: MIT License
Classifier: Operating System :: POSIX :: Linux
Classifier: Operating System :: POSIX :: SunOS/Solaris
Classifier: Programming Language :: Python :: 2
Classifier: Programming Language :: Python :: 2.6
Classifier: Programming Language :: Python :: 2.7
Classifier: Topic :: Utilities
